{
  "id": "games-16-ranch-trail-run",
  "name": "Ranch Trail Run",
  "category": "games",
  "format": "for_time",
  "format_meta": {},
  "movements": [
    {
      "exercise": "run",
      "distance_m": 7000
    }
  ],
  "partition": null,
  "scaling": null,
  "origin": null,
  "tags": [
    "games",
    "2016",
    "running",
    "outdoor",
    "endurance"
  ],
  "source_notes": "games.crossfit.com/workouts/games/2016/1 (official CrossFit Games event), retrieved 2026-07-09",
  "schema_version": "1.1",
  "last_updated": "2026-07-09"
}
