{
  "id": "open-18-5",
  "name": "18.5",
  "category": "open",
  "format": "amrap",
  "format_meta": {
    "time_cap_minutes": 7,
    "scoring": "reps"
  },
  "movements": [
    {
      "exercise": "thruster",
      "reps": [
        3,
        6,
        9,
        12,
        15,
        18
      ],
      "load": {
        "rx_male": "100lb",
        "rx_female": "65lb"
      }
    },
    {
      "exercise": "chest-to-bar-pull-up",
      "reps": [
        3,
        6,
        9,
        12,
        15,
        18
      ]
    }
  ],
  "partition": null,
  "scaling": null,
  "origin": null,
  "tags": [
    "open",
    "2018",
    "barbell",
    "gymnastics",
    "ascending"
  ],
  "description": "A 7-minute ascending thruster-and-chest-to-bar-pull-up couplet, climbing by threes up to 18.",
  "source_notes": "games.crossfit.com/workouts/open/2018/5 (official CrossFit Games Open workout), retrieved 2026-07-09; ascending ladder (+3 reps each round) continues indefinitely until the 7-minute cap",
  "schema_version": "1.1",
  "last_updated": "2026-07-09"
}
